mmh3.cpython-38-x86_64-linux-gnu.so
mmhash3-3.0.1.dist-info/LICENSE
mmhash3-3.0.1.dist-info/top_level.txt
mmhash3-3.0.1.dist-info/WHEEL
mmhash3-3.0.1.dist-info/RECORD
mmhash3-3.0.1.dist-info/METADATA
