Metadata-Version: 2.1
Name: mmhash3
Version: 3.0.1
Summary: Python wrapper for MurmurHash (MurmurHash3), a set of fast and robust hash functions.
Home-page: https://github.com/Fokko/mmhash
Author: Hajime Senuma
Author-email: hajime.senuma@gmail.com
License: License :: CC0 1.0 Universal (CC0 1.0) Public Domain Dedication
Keywords: utility hash MurmurHash
Platform: UNKNOWN
Classifier: Development Status :: 5 - Production/Stable
Classifier: Intended Audience :: Developers
Classifier: License :: CC0 1.0 Universal (CC0 1.0) Public Domain Dedication
Classifier: Programming Language :: Python :: 3
Classifier: Programming Language :: Python :: 3.6
Classifier: Programming Language :: Python :: 3.7
Classifier: Programming Language :: Python :: 3.8
Classifier: Programming Language :: Python :: 3.9
Classifier: Programming Language :: Python :: 3.10
Classifier: Programming Language :: Python :: 3.11
Classifier: Topic :: Software Development :: Libraries
Classifier: Topic :: Utilities
License-File: LICENSE
